{
    "address1": "1170 Peachtree Street, N.E.",
    "address2": "Suite 2300",
    "city": "Atlanta",
    "state": "GA",
    "zip": "30309-7676",
    "country": "United States",
    "phone": "404 853 1400",
    "website": "https://www.acuitybrands.com",
    "industry": "Electrical Equipment & Parts",
    "industryDisp": "Electrical Equipment & Parts",
    "sector": "Industrials",
    "sectorDisp": "Industrials",
    "longBusinessSummary": "Acuity Brands, Inc. provides lighting and building management solutions in North America and internationally. The company operates through two segments, Acuity Brands Lighting and Lighting Controls (ABL); and the Intelligent Spaces Group (ISG). The ABL segment provides commercial, architectural, and specialty lighting solutions, as well as lighting controls and components for various indoor and outdoor applications under the Lithonia Lighting, Holophane, Peerless, Gotham, Mark Architectural Lighting, Winona Lighting, Juno, Indy, Aculux, Healthcare Lighting, Hydrel, American Electric Lighting, Sunoptics, eldoLED, nLight, Sensor Switch, IOTA, A-Light, Cyclone, Eureka, Lumniaire LED, Luminis, Dark to Light, RELOC Wiring Solutions, and OPTOTRONIC brands. This segment serves electrical distributors, retail home improvement centers, electric utilities, national accounts, original equipment manufacturers, digital retailers, lighting showrooms, and energy service companies. The ISG segment offers building management platform and location-aware applications under the Distech Controls and Atrius brands. This segment serves system integrators, as well as retail stores, airports, and enterprise campuses. Acuity Brands, Inc. was incorporated in 2001 and is headquartered in Atlanta, Georgia.",
    "fullTimeEmployees": 13000,
    "companyOfficers": [
        {
            "maxAge": 1,
            "name": "Mr. Neil M. Ashe",
            "age": 54,
            "title": "Chairman, Pres & CEO",
            "yearBorn": 1968,
            "fiscalYear": 2022,
            "totalPay": 2099979,
            "exercisedValue": 0,
            "unexercisedValue": 10949306
        },
        {
            "maxAge": 1,
            "name": "Ms. Karen J. Holcom",
            "age": 53,
            "title": "Sr. VP & CFO",
            "yearBorn": 1969,
            "fiscalYear": 2022,
            "totalPay": 999550,
            "exercisedValue": 316218,
            "unexercisedValue": 151915
        },
        {
            "maxAge": 1,
            "name": "Mr. Barry R. Goldman",
            "age": 55,
            "title": "Sr. VP & Gen. Counsel",
            "yearBorn": 1967,
            "fiscalYear": 2022,
            "totalPay": 857420,
            "exercisedValue": 0,
            "unexercisedValue": 152868
        },
        {
            "maxAge": 1,
            "name": "Ms. Dianne S. Mills",
            "age": 61,
            "title": "Sr. VP & Chief HR Officer",
            "yearBorn": 1961,
            "fiscalYear": 2022,
            "totalPay": 878322,
            "exercisedValue": 0,
            "unexercisedValue": 0
        },
        {
            "maxAge": 1,
            "name": "Ms. Charlotte  McLaughlin",
            "title": "VP of Investor Relations",
            "exercisedValue": 0,
            "unexercisedValue": 0
        },
        {
            "maxAge": 1,
            "name": "April  Appling",
            "title": "VP of Corp. Communications & Events",
            "exercisedValue": 0,
            "unexercisedValue": 0
        },
        {
            "maxAge": 1,
            "name": "Mr. Philippe  Brzusczak",
            "title": "Sr. VP of Corp. Devel. & Strategy",
            "exercisedValue": 0,
            "unexercisedValue": 0
        },
        {
            "maxAge": 1,
            "name": "Mr. C. Dan Smith Jr.",
            "age": 57,
            "title": "Sr. VP & Treasurer",
            "yearBorn": 1965,
            "fiscalYear": 2009,
            "exercisedValue": 0,
            "unexercisedValue": 0
        },
        {
            "maxAge": 1,
            "name": "Mr. Laurent J. Vernerey",
            "age": 62,
            "title": "Strategic Bus. Devel. Exec.",
            "yearBorn": 1960,
            "fiscalYear": 2019,
            "exercisedValue": 0,
            "unexercisedValue": 0
        },
        {
            "maxAge": 1,
            "name": "Mr. Trevor S. Palmer",
            "title": "Pres of Acuity Brands Lighting & Controls",
            "exercisedValue": 0,
            "unexercisedValue": 0
        }
    ],
    "auditRisk": 1,
    "boardRisk": 3,
    "compensationRisk": 6,
    "shareHolderRightsRisk": 1,
    "overallRisk": 1,
    "governanceEpochDate": 1693526400,
    "compensationAsOfEpochDate": 1672444800,
    "maxAge": 86400,
    "priceHint": 2,
    "previousClose": 158.68,
    "open": 158.61,
    "dayLow": 156.495,
    "dayHigh": 159.98,
    "regularMarketPreviousClose": 158.68,
    "regularMarketOpen": 158.61,
    "regularMarketDayLow": 156.495,
    "regularMarketDayHigh": 159.98,
    "dividendRate": 0.52,
    "dividendYield": 0.0033000002,
    "exDividendDate": 1689552000,
    "payoutRatio": 0.045,
    "fiveYearAvgDividendYield": 0.37,
    "beta": 1.531811,
    "trailingPE": 13.790476,
    "forwardPE": 12.039305,
    "volume": 243399,
    "regularMarketVolume": 243399,
    "averageVolume": 339369,
    "averageVolume10days": 264770,
    "averageDailyVolume10Day": 264770,
    "bid": 0.0,
    "ask": 0.0,
    "bidSize": 900,
    "askSize": 800,
    "marketCap": 4968325632,
    "fiftyTwoWeekLow": 149.3,
    "fiftyTwoWeekHigh": 202.9,
    "priceToSalesTrailing12Months": 1.2261113,
    "fiftyDayAverage": 163.0566,
    "twoHundredDayAverage": 170.75784,
    "trailingAnnualDividendRate": 0.52,
    "trailingAnnualDividendYield": 0.0032770357,
    "currency": "USD",
    "enterpriseValue": 5153842176,
    "profitMargins": 0.09340999,
    "floatShares": 30809923,
    "sharesOutstanding": 31192400,
    "sharesShort": 2830784,
    "sharesShortPriorMonth": 2633747,
    "sharesShortPreviousMonthDate": 1689292800,
    "dateShortInterest": 1692057600,
    "sharesPercentSharesOut": 0.0908,
    "heldPercentInsiders": 0.00184,
    "heldPercentInstitutions": 1.02206,
    "shortRatio": 9.71,
    "shortPercentOfFloat": 0.1254,
    "impliedSharesOutstanding": 31192400,
    "bookValue": 63.449,
    "priceToBook": 2.5103626,
    "lastFiscalYearEnd": 1661904000,
    "nextFiscalYearEnd": 1693440000,
    "mostRecentQuarter": 1685491200,
    "earningsQuarterlyGrowth": -0.007,
    "netIncomeToCommon": 378500000,
    "trailingEps": 11.55,
    "forwardEps": 13.23,
    "pegRatio": 0.9,
    "enterpriseToRevenue": 1.272,
    "enterpriseToEbitda": 8.457,
    "52WeekChange": -0.08137727,
    "SandP52WeekChange": 0.08443928,
    "lastDividendValue": 0.13,
    "lastDividendDate": 1689552000,
    "exchange": "NYQ",
    "quoteType": "EQUITY",
    "symbol": "AYI",
    "underlyingSymbol": "AYI",
    "shortName": "Acuity Brands, Inc.",
    "longName": "Acuity Brands, Inc.",
    "firstTradeDateEpochUtc": 1007389800,
    "timeZoneFullName": "America/New_York",
    "timeZoneShortName": "EDT",
    "uuid": "95e22515-3462-3f63-be59-76e75ce33dd6",
    "messageBoardId": "finmb_1413208",
    "gmtOffSetMilliseconds": -14400000,
    "currentPrice": 159.28,
    "targetHighPrice": 210.0,
    "targetLowPrice": 170.0,
    "targetMeanPrice": 182.57,
    "targetMedianPrice": 180.0,
    "recommendationMean": 2.6,
    "recommendationKey": "hold",
    "numberOfAnalystOpinions": 7,
    "totalCash": 359300000,
    "totalCashPerShare": 11.631,
    "ebitda": 609400000,
    "totalDebt": 592600000,
    "quickRatio": 1.449,
    "currentRatio": 2.256,
    "totalRevenue": 4052100096,
    "debtToEquity": 30.084,
    "revenuePerShare": 125.872,
    "returnOnAssets": 0.09207,
    "returnOnEquity": 0.19468,
    "grossProfits": 1672700000,
    "freeCashflow": 489449984,
    "operatingCashflow": 622099968,
    "earningsGrowth": 0.068,
    "revenueGrowth": -0.057,
    "grossMargins": 0.42768002,
    "ebitdaMargins": 0.15039,
    "operatingMargins": 0.12823,
    "financialCurrency": "USD",
    "trailingPegRatio": 1.2781,
    "parent_etfs": [
        "PAVE"
    ]
}