{
    "address1": "2 Canal Park",
    "address2": "4th Floor",
    "city": "Cambridge",
    "state": "MA",
    "zip": "02141",
    "country": "United States",
    "phone": "617 354 0068",
    "website": "https://www.cargurus.com",
    "industry": "Auto & Truck Dealerships",
    "sector": "Consumer Cyclical",
    "longBusinessSummary": "CarGurus, Inc. operates an online automotive marketplace connecting buyers and sellers of new and used cars in the United States and internationally. It operates through two segments, U.S. Marketplace and Digital Wholesale The company provides consumers an online automotive marketplace where they can search for new and used car listings from its dealers, as well as sell their car to dealers and other consumers. Its marketplace connects dealers to a large audience of informed and engaged consumers. The company operates online marketplaces under the CarGurus brand in Canada and the United Kingdom; Autolist and CarOffer brands in the United States; and PistonHeads brand in the United Kingdom. CarGurus, Inc. was founded in 2005 and is headquartered in Cambridge, Massachusetts.",
    "fullTimeEmployees": 1403,
    "companyOfficers": [
        {
            "maxAge": 1,
            "name": "Mr. E. Langley Steinert",
            "age": 58,
            "title": "Founder & Exec. Chairman",
            "yearBorn": 1964,
            "fiscalYear": 2022,
            "totalPay": 10000,
            "exercisedValue": 0,
            "unexercisedValue": 0
        },
        {
            "maxAge": 1,
            "name": "Mr. Jason M. Trevisan",
            "age": 47,
            "title": "CEO, Treasurer & Director",
            "yearBorn": 1975,
            "fiscalYear": 2022,
            "totalPay": 1001838,
            "exercisedValue": 0,
            "unexercisedValue": 0
        },
        {
            "maxAge": 1,
            "name": "Mr. Matthew Todd Quinn",
            "age": 50,
            "title": "Chief Technology Officer",
            "yearBorn": 1972,
            "fiscalYear": 2022,
            "totalPay": 533597,
            "exercisedValue": 0,
            "unexercisedValue": 0
        },
        {
            "maxAge": 1,
            "name": "Ms. Andrea Lee Eldridge",
            "age": 46,
            "title": "Chief People Officer",
            "yearBorn": 1976,
            "fiscalYear": 2022,
            "totalPay": 505763,
            "exercisedValue": 0,
            "unexercisedValue": 0
        },
        {
            "maxAge": 1,
            "name": "Mr. Samuel  Zales",
            "age": 58,
            "title": "COO & Pres",
            "yearBorn": 1964,
            "fiscalYear": 2021,
            "exercisedValue": 0,
            "unexercisedValue": 0
        },
        {
            "maxAge": 1,
            "name": "Mr. Yann Bruno Gellot",
            "age": 50,
            "title": "Principal Accounting Officer",
            "yearBorn": 1972,
            "exercisedValue": 0,
            "unexercisedValue": 0
        },
        {
            "maxAge": 1,
            "name": "Ms. Kirndeep  Singh",
            "title": "VP & Head of Investor Relations",
            "exercisedValue": 0,
            "unexercisedValue": 0
        },
        {
            "maxAge": 1,
            "name": "Mr. Javier  Zamora",
            "age": 51,
            "title": "Gen. Counsel & Corp. Sec.",
            "yearBorn": 1971,
            "exercisedValue": 0,
            "unexercisedValue": 0
        },
        {
            "maxAge": 1,
            "name": "Brian  Kramer",
            "title": "Director of PR",
            "exercisedValue": 0,
            "unexercisedValue": 0
        },
        {
            "maxAge": 1,
            "name": "Ms. Dafna  Sarnoff",
            "age": 58,
            "title": "Chief Marketing Officer",
            "yearBorn": 1964,
            "fiscalYear": 2021,
            "exercisedValue": 0,
            "unexercisedValue": 0
        }
    ],
    "auditRisk": 6,
    "boardRisk": 10,
    "compensationRisk": 8,
    "shareHolderRightsRisk": 10,
    "overallRisk": 10,
    "governanceEpochDate": 1693526400,
    "compensationAsOfEpochDate": 1672444800,
    "maxAge": 86400,
    "priceHint": 2,
    "previousClose": 18.33,
    "open": 18.41,
    "dayLow": 18.29,
    "dayHigh": 18.7804,
    "regularMarketPreviousClose": 18.33,
    "regularMarketOpen": 18.41,
    "regularMarketDayLow": 18.29,
    "regularMarketDayHigh": 18.7804,
    "payoutRatio": 0.0,
    "beta": 1.625864,
    "trailingPE": 12.75,
    "forwardPE": 14.926829,
    "volume": 1610404,
    "regularMarketVolume": 1610404,
    "averageVolume": 1646562,
    "averageVolume10days": 984580,
    "averageDailyVolume10Day": 984580,
    "bid": 0.0,
    "ask": 0.0,
    "bidSize": 1000,
    "askSize": 1400,
    "marketCap": 2083823360,
    "fiftyTwoWeekLow": 9.142,
    "fiftyTwoWeekHigh": 24.22,
    "priceToSalesTrailing12Months": 1.7586521,
    "fiftyDayAverage": 20.4796,
    "twoHundredDayAverage": 17.887276,
    "trailingAnnualDividendRate": 0.0,
    "trailingAnnualDividendYield": 0.0,
    "currency": "USD",
    "enterpriseValue": 1867195904,
    "profitMargins": 0.25214002,
    "floatShares": 77534021,
    "sharesOutstanding": 97499000,
    "sharesShort": 9129682,
    "sharesShortPriorMonth": 9809749,
    "sharesShortPreviousMonthDate": 1689292800,
    "dateShortInterest": 1692057600,
    "sharesPercentSharesOut": 0.0804,
    "heldPercentInsiders": 0.01805,
    "heldPercentInstitutions": 1.0619999,
    "shortRatio": 6.51,
    "shortPercentOfFloat": 0.1113,
    "bookValue": 6.179,
    "priceToBook": 2.9713547,
    "lastFiscalYearEnd": 1672444800,
    "nextFiscalYearEnd": 1703980800,
    "mostRecentQuarter": 1688083200,
    "netIncomeToCommon": 298756000,
    "trailingEps": 1.44,
    "forwardEps": 1.23,
    "pegRatio": 1.28,
    "enterpriseToRevenue": 1.576,
    "enterpriseToEbitda": 14.648,
    "exchange": "NMS",
    "quoteType": "EQUITY",
    "symbol": "CARG",
    "underlyingSymbol": "CARG",
    "shortName": "CarGurus, Inc.",
    "longName": "CarGurus, Inc.",
    "firstTradeDateEpochUtc": 1507815000,
    "timeZoneFullName": "America/New_York",
    "timeZoneShortName": "EDT",
    "gmtOffSetMilliseconds": -14400000,
    "currentPrice": 18.36,
    "targetHighPrice": 28.0,
    "targetLowPrice": 15.0,
    "targetMeanPrice": 22.91,
    "targetMedianPrice": 22.0,
    "recommendationMean": 2.1,
    "recommendationKey": "buy",
    "numberOfAnalystOpinions": 11,
    "totalCash": 453550016,
    "totalCashPerShare": 3.996,
    "ebitda": 127474000,
    "totalDebt": 207054000,
    "quickRatio": 4.436,
    "currentRatio": 4.833,
    "totalRevenue": 1184898048,
    "debtToEquity": 28.336,
    "revenuePerShare": 10.165,
    "returnOnAssets": 0.055019997,
    "returnOnEquity": 0.092980005,
    "grossProfits": 657718000,
    "freeCashflow": 237340368,
    "operatingCashflow": 264192000,
    "revenueGrowth": -0.531,
    "grossMargins": 0.51237,
    "ebitdaMargins": 0.107580006,
    "operatingMargins": 0.07616,
    "financialCurrency": "USD",
    "trailingPegRatio": 1.1209,
    "parent_etfs": [
        "MILN"
    ]
}