{
    "address1": "3001 Bishop Drive",
    "address2": "Suite 350",
    "city": "San Ramon",
    "state": "CA",
    "zip": "94583",
    "country": "United States",
    "phone": "925 201 2000",
    "website": "https://www.five9.com",
    "industry": "Software\u2014Infrastructure",
    "sector": "Technology",
    "longBusinessSummary": "Five9, Inc., together with its subsidiaries, provides intelligent cloud software for contact centers in the United States and internationally. The company offers virtual contact center cloud platform that delivers a suite of applications, which enables the breadth of contact center-related customer service, sales, and marketing functions. Its platform allows to manage and optimize customer interactions across voice, chat, email, web, social media, and mobile channels directly or through its application programming interfaces. The company serves customers in various industries, such as banking and financial services, business process outsourcers, retail, healthcare, technology, and education. Five9, Inc. was incorporated in 2001 and is headquartered in San Ramon, California.",
    "fullTimeEmployees": 2380,
    "companyOfficers": [
        {
            "maxAge": 1,
            "name": "Mr. Michael  Burkland M.B.A.",
            "age": 59,
            "title": "CEO & Chairman",
            "yearBorn": 1963,
            "fiscalYear": 2022,
            "totalPay": 748898,
            "exercisedValue": 0,
            "unexercisedValue": 21990084
        },
        {
            "maxAge": 1,
            "name": "Mr. Daniel P. Burkland",
            "age": 57,
            "title": "Pres & Chief Revenue Officer",
            "yearBorn": 1965,
            "fiscalYear": 2022,
            "totalPay": 891109,
            "exercisedValue": 0,
            "unexercisedValue": 13789453
        },
        {
            "maxAge": 1,
            "name": "Mr. Barry  Zwarenstein",
            "age": 73,
            "title": "Chief Financial Officer",
            "yearBorn": 1949,
            "fiscalYear": 2022,
            "totalPay": 703422,
            "exercisedValue": 4589363,
            "unexercisedValue": 3319892
        },
        {
            "maxAge": 1,
            "name": "Mr. Panos  Kozanian",
            "title": "Exec. VP of Product Engineering",
            "fiscalYear": 2022,
            "totalPay": 605381,
            "exercisedValue": 0,
            "unexercisedValue": 0
        },
        {
            "maxAge": 1,
            "name": "Mr. James B. Doran",
            "age": 49,
            "title": "Exec. VP of Strategy & Operations",
            "yearBorn": 1973,
            "fiscalYear": 2018,
            "exercisedValue": 0,
            "unexercisedValue": 0
        },
        {
            "maxAge": 1,
            "name": "Ms. Leena  Mansharamani",
            "age": 54,
            "title": "Chief Accounting Officer & Corp. Controller",
            "yearBorn": 1968,
            "exercisedValue": 0,
            "unexercisedValue": 0
        },
        {
            "maxAge": 1,
            "name": "Dr. Jonathan D. Rosenberg Ph.D.",
            "age": 50,
            "title": "CTO & Head of AI",
            "yearBorn": 1972,
            "fiscalYear": 2019,
            "exercisedValue": 0,
            "unexercisedValue": 0
        },
        {
            "maxAge": 1,
            "name": "Ms. Kimberly G. Lytikainen",
            "age": 55,
            "title": "Chief Legal & Compliance Officer and Corp. Sec.",
            "yearBorn": 1967,
            "exercisedValue": 0,
            "unexercisedValue": 0
        },
        {
            "maxAge": 1,
            "name": "Ms. Tricia  Yankovich",
            "title": "Chief People Officer",
            "exercisedValue": 0,
            "unexercisedValue": 0
        },
        {
            "maxAge": 1,
            "name": "Mr. Callan  Schebella",
            "title": "Exec. VP of Product Management",
            "exercisedValue": 0,
            "unexercisedValue": 0
        }
    ],
    "auditRisk": 7,
    "boardRisk": 8,
    "compensationRisk": 10,
    "shareHolderRightsRisk": 8,
    "overallRisk": 10,
    "governanceEpochDate": 1693526400,
    "compensationAsOfEpochDate": 1672444800,
    "maxAge": 86400,
    "priceHint": 2,
    "previousClose": 70.06,
    "open": 70.2,
    "dayLow": 68.33,
    "dayHigh": 71.2023,
    "regularMarketPreviousClose": 70.06,
    "regularMarketOpen": 70.2,
    "regularMarketDayLow": 68.33,
    "regularMarketDayHigh": 71.2023,
    "payoutRatio": 0.0,
    "beta": 0.757607,
    "forwardPE": 31.795347,
    "volume": 538547,
    "regularMarketVolume": 538547,
    "averageVolume": 1038772,
    "averageVolume10days": 855010,
    "averageDailyVolume10Day": 855010,
    "bid": 0.0,
    "ask": 0.0,
    "bidSize": 1200,
    "askSize": 900,
    "marketCap": 4936433152,
    "fiftyTwoWeekLow": 46.61,
    "fiftyTwoWeekHigh": 93.3,
    "priceToSalesTrailing12Months": 5.8212104,
    "fiftyDayAverage": 77.8928,
    "twoHundredDayAverage": 70.85485,
    "trailingAnnualDividendRate": 0.0,
    "trailingAnnualDividendYield": 0.0,
    "currency": "USD",
    "enterpriseValue": 5193644544,
    "profitMargins": -0.10123,
    "floatShares": 71056193,
    "sharesOutstanding": 72212304,
    "sharesShort": 3061010,
    "sharesShortPriorMonth": 3670805,
    "sharesShortPreviousMonthDate": 1689292800,
    "dateShortInterest": 1692057600,
    "sharesPercentSharesOut": 0.0424,
    "heldPercentInsiders": 0.00966,
    "heldPercentInstitutions": 1.01209,
    "shortRatio": 2.44,
    "shortPercentOfFloat": 0.0428,
    "bookValue": 6.356,
    "priceToBook": 10.755192,
    "lastFiscalYearEnd": 1672444800,
    "nextFiscalYearEnd": 1703980800,
    "mostRecentQuarter": 1688083200,
    "netIncomeToCommon": -85847000,
    "trailingEps": -1.2,
    "forwardEps": 2.15,
    "pegRatio": 1.86,
    "enterpriseToRevenue": 6.125,
    "enterpriseToEbitda": -164.595,
    "exchange": "NGM",
    "quoteType": "EQUITY",
    "symbol": "FIVN",
    "underlyingSymbol": "FIVN",
    "shortName": "Five9, Inc.",
    "longName": "Five9, Inc.",
    "firstTradeDateEpochUtc": 1396618200,
    "timeZoneFullName": "America/New_York",
    "timeZoneShortName": "EDT",
    "gmtOffSetMilliseconds": -14400000,
    "currentPrice": 68.36,
    "targetHighPrice": 105.0,
    "targetLowPrice": 61.0,
    "targetMeanPrice": 88.52,
    "targetMedianPrice": 90.0,
    "recommendationMean": 2.2,
    "recommendationKey": "buy",
    "numberOfAnalystOpinions": 23,
    "totalCash": 659836032,
    "totalCashPerShare": 9.137,
    "ebitda": -31554000,
    "totalDebt": 794286016,
    "quickRatio": 4.747,
    "currentRatio": 5.316,
    "totalRevenue": 848008000,
    "debtToEquity": 173.123,
    "revenuePerShare": 11.95,
    "returnOnAssets": -0.03724,
    "returnOnEquity": -0.24399,
    "grossProfits": 412045000,
    "freeCashflow": 196856752,
    "operatingCashflow": 118530000,
    "revenueGrowth": 0.177,
    "grossMargins": 0.52933997,
    "ebitdaMargins": -0.03721,
    "operatingMargins": -0.09064,
    "financialCurrency": "USD",
    "trailingPegRatio": 1.4435,
    "parent_etfs": [
        "CLOU"
    ]
}