{
    "address1": "3220 Tillman Drive",
    "address2": "Suite 300",
    "city": "Bensalem",
    "state": "PA",
    "zip": "19020",
    "country": "United States",
    "phone": "215 639 4274",
    "website": "https://www.hcsgcorp.com",
    "industry": "Medical Care Facilities",
    "sector": "Healthcare",
    "longBusinessSummary": "Healthcare Services Group, Inc. provides management, administrative, and operating services to the housekeeping, laundry, linen, facility maintenance, and dietary service departments of nursing homes, retirement complexes, rehabilitation centers, and hospitals in the United States. It operates through two segments, Housekeeping and Dietary. The Housekeeping segment engages in the cleaning, disinfecting, and sanitizing of resident rooms and common areas of the customers' facilities, as well as laundering and processing of the bed linens, uniforms, resident personal clothing, and other assorted linen items utilized at the customers' facilities. The Dietary segment provides food purchasing, meal preparation, and professional dietitian services, which include the development of menus that meet the dietary needs of residents. This segment also offers on-site management and clinical consulting services to facilities. Healthcare Services Group, Inc. was incorporated in 1976 and is based in Bensalem, Pennsylvania.",
    "fullTimeEmployees": 35700,
    "companyOfficers": [
        {
            "maxAge": 1,
            "name": "Mr. Theodore  Wahl CPA",
            "age": 48,
            "title": "Pres, CEO & Director",
            "yearBorn": 1974,
            "fiscalYear": 2022,
            "totalPay": 1388932,
            "exercisedValue": 0,
            "unexercisedValue": 0
        },
        {
            "maxAge": 1,
            "name": "Mr. Andrew W. Kush AAI",
            "age": 44,
            "title": "Exec. VP & COO",
            "yearBorn": 1978,
            "fiscalYear": 2022,
            "totalPay": 764228,
            "exercisedValue": 0,
            "unexercisedValue": 0
        },
        {
            "maxAge": 1,
            "name": "Mr. Andrew M. Brophy CPA",
            "age": 32,
            "title": "VP, Controller & Principal Accounting Officer",
            "yearBorn": 1990,
            "fiscalYear": 2022,
            "totalPay": 285438,
            "exercisedValue": 0,
            "unexercisedValue": 0
        },
        {
            "maxAge": 1,
            "name": "Mr. John Christopher Shea CPA, CPA, M.B.A., MBA",
            "age": 50,
            "title": "Exec. VP & Chief Admin. Officer",
            "yearBorn": 1972,
            "fiscalYear": 2022,
            "totalPay": 694675,
            "exercisedValue": 0,
            "unexercisedValue": 0
        },
        {
            "maxAge": 1,
            "name": "Mr. Patrick J. Orr Esq.",
            "age": 47,
            "title": "EVP & Chief Revenue Officer",
            "yearBorn": 1975,
            "fiscalYear": 2022,
            "totalPay": 616291,
            "exercisedValue": 0,
            "unexercisedValue": 0
        },
        {
            "maxAge": 1,
            "name": "Mr. Jason J. Bundick Esq.",
            "age": 45,
            "title": "Exec. VP, Chief Compliance Officer, Gen. Counsel & Sec.",
            "yearBorn": 1977,
            "fiscalYear": 2021,
            "exercisedValue": 0,
            "unexercisedValue": 0
        },
        {
            "maxAge": 1,
            "name": "Mr. Matthew J. McKee MBA",
            "title": "Chief Communications Officer",
            "exercisedValue": 0,
            "unexercisedValue": 0
        },
        {
            "maxAge": 1,
            "name": "Mr. Bryan D. McCartney",
            "age": 61,
            "title": "Exec. VP",
            "yearBorn": 1961,
            "fiscalYear": 2016,
            "exercisedValue": 0,
            "unexercisedValue": 0
        }
    ],
    "auditRisk": 7,
    "boardRisk": 4,
    "compensationRisk": 3,
    "shareHolderRightsRisk": 3,
    "overallRisk": 3,
    "governanceEpochDate": 1693526400,
    "compensationAsOfEpochDate": 1672444800,
    "maxAge": 86400,
    "priceHint": 2,
    "previousClose": 11.07,
    "open": 11.06,
    "dayLow": 10.8946,
    "dayHigh": 11.12,
    "regularMarketPreviousClose": 11.07,
    "regularMarketOpen": 11.06,
    "regularMarketDayLow": 10.8946,
    "regularMarketDayHigh": 11.12,
    "exDividendDate": 1668643200,
    "payoutRatio": 0.82449996,
    "fiveYearAvgDividendYield": 3.77,
    "beta": 0.411825,
    "trailingPE": 21.173079,
    "forwardPE": 14.115385,
    "volume": 998254,
    "regularMarketVolume": 998254,
    "averageVolume": 729335,
    "averageVolume10days": 519050,
    "averageDailyVolume10Day": 519050,
    "bid": 0.0,
    "ask": 0.0,
    "bidSize": 2900,
    "askSize": 1100,
    "marketCap": 816886976,
    "fiftyTwoWeekLow": 10.88,
    "fiftyTwoWeekHigh": 15.97,
    "priceToSalesTrailing12Months": 0.4877901,
    "fiftyDayAverage": 13.0712,
    "twoHundredDayAverage": 13.5141,
    "trailingAnnualDividendRate": 0.215,
    "trailingAnnualDividendYield": 0.019421862,
    "currency": "USD",
    "enterpriseValue": 752639936,
    "profitMargins": 0.022550002,
    "floatShares": 69499940,
    "sharesOutstanding": 74195000,
    "sharesShort": 2128371,
    "sharesShortPriorMonth": 3993098,
    "sharesShortPreviousMonthDate": 1689292800,
    "dateShortInterest": 1692057600,
    "sharesPercentSharesOut": 0.0287,
    "heldPercentInsiders": 0.0077899997,
    "heldPercentInstitutions": 1.02212,
    "shortRatio": 2.35,
    "shortPercentOfFloat": 0.0401,
    "bookValue": 6.073,
    "priceToBook": 1.8129426,
    "lastFiscalYearEnd": 1672444800,
    "nextFiscalYearEnd": 1703980800,
    "mostRecentQuarter": 1688083200,
    "earningsQuarterlyGrowth": 0.261,
    "netIncomeToCommon": 37763000,
    "trailingEps": 0.52,
    "forwardEps": 0.78,
    "pegRatio": 1.89,
    "lastSplitFactor": "3:2",
    "lastSplitDate": 1289779200,
    "enterpriseToRevenue": 0.449,
    "enterpriseToEbitda": 13.483,
    "exchange": "NMS",
    "quoteType": "EQUITY",
    "symbol": "HCSG",
    "underlyingSymbol": "HCSG",
    "shortName": "Healthcare Services Group, Inc.",
    "longName": "Healthcare Services Group, Inc.",
    "firstTradeDateEpochUtc": 438964200,
    "timeZoneFullName": "America/New_York",
    "timeZoneShortName": "EDT",
    "gmtOffSetMilliseconds": -14400000,
    "currentPrice": 11.01,
    "targetHighPrice": 18.0,
    "targetLowPrice": 14.0,
    "targetMeanPrice": 15.6,
    "targetMedianPrice": 15.0,
    "recommendationMean": 2.7,
    "recommendationKey": "hold",
    "numberOfAnalystOpinions": 5,
    "totalCash": 121847000,
    "totalCashPerShare": 1.642,
    "ebitda": 55822000,
    "totalDebt": 57600000,
    "quickRatio": 2.651,
    "currentRatio": 2.895,
    "totalRevenue": 1674669056,
    "debtToEquity": 12.783,
    "revenuePerShare": 22.505,
    "returnOnAssets": 0.03783,
    "returnOnEquity": 0.08501001,
    "grossProfits": 193840000,
    "freeCashflow": -14692875,
    "operatingCashflow": 4110000,
    "earningsGrowth": 0.283,
    "revenueGrowth": -0.014,
    "grossMargins": 0.12078,
    "ebitdaMargins": 0.03333,
    "operatingMargins": 0.027139999,
    "financialCurrency": "USD",
    "trailingPegRatio": 1.6599,
    "parent_etfs": [
        "BFIT"
    ]
}