{
    "address1": "1 Yingbin Avenue",
    "address2": "Shangrao Economic Development Zone",
    "city": "Shang Rao",
    "zip": "334100",
    "country": "China",
    "phone": "86 79 3858 8188",
    "fax": "86 79 3846 1152",
    "website": "https://www.jinkosolar.com",
    "industry": "Solar",
    "industryDisp": "Solar",
    "sector": "Technology",
    "sectorDisp": "Technology",
    "longBusinessSummary": "JinkoSolar Holding Co., Ltd., together with its subsidiaries, engages in the design, development, production, and marketing of photovoltaic products. The company offers solar modules, silicon wafers, solar cells, recovered silicon materials, and silicon ingots. It also provides solar system integration services; and develops commercial solar power projects. The company sells its products to distributors, project developers, system integrators, and manufacturers of solar power products under the JinkoSolar brand. As of December 31, 2022, it had an integrated annual capacity of 65 gigawatts (GW) for mono wafers; 55 GW for solar cells; and 70 GW for solar modules. The company has operations in the People's Republic of China, the United States, Mexico, Australia, Japan, United Arab Emirates, Turkey, Jordan, Vietnam, Egypt, Spain, and Germany. JinkoSolar Holding Co., Ltd. was founded in 2006 and is headquartered in Shangrao, the People's Republic of China.",
    "fullTimeEmployees": 46511,
    "companyOfficers": [
        {
            "maxAge": 1,
            "name": "Mr. Xiande  Li",
            "age": 47,
            "title": "Co-Founder, CEO & Chairman",
            "yearBorn": 1975,
            "exercisedValue": 0,
            "unexercisedValue": 0
        },
        {
            "maxAge": 1,
            "name": "Mr. Xianhua  Li",
            "age": 48,
            "title": "Co-Founder & Director",
            "yearBorn": 1974,
            "exercisedValue": 0,
            "unexercisedValue": 0
        },
        {
            "maxAge": 1,
            "name": "Mr. Mengmeng  Li",
            "age": 41,
            "title": "Chief Financial Officer",
            "yearBorn": 1981,
            "exercisedValue": 0,
            "unexercisedValue": 0
        },
        {
            "maxAge": 1,
            "name": "Mr. Sebastian  Liu",
            "title": "Director of IR",
            "exercisedValue": 0,
            "unexercisedValue": 0
        },
        {
            "maxAge": 1,
            "name": "Stella  Wang",
            "title": "Investor Relations Officer",
            "exercisedValue": 0,
            "unexercisedValue": 0
        }
    ],
    "maxAge": 86400,
    "priceHint": 2,
    "previousClose": 29.82,
    "open": 30.08,
    "dayLow": 28.76,
    "dayHigh": 30.09,
    "regularMarketPreviousClose": 29.82,
    "regularMarketOpen": 30.08,
    "regularMarketDayLow": 28.76,
    "regularMarketDayHigh": 30.09,
    "payoutRatio": 0.0,
    "beta": 0.855117,
    "trailingPE": 3.3932323,
    "forwardPE": 3.4660308,
    "volume": 921191,
    "regularMarketVolume": 921191,
    "averageVolume": 798024,
    "averageVolume10days": 797290,
    "averageDailyVolume10Day": 797290,
    "bid": 0.0,
    "ask": 0.0,
    "bidSize": 1200,
    "askSize": 1800,
    "marketCap": 1494176896,
    "fiftyTwoWeekLow": 28.76,
    "fiftyTwoWeekHigh": 63.08,
    "priceToSalesTrailing12Months": 0.014431537,
    "fiftyDayAverage": 38.3342,
    "twoHundredDayAverage": 46.06225,
    "trailingAnnualDividendRate": 0.0,
    "trailingAnnualDividendYield": 0.0,
    "currency": "USD",
    "enterpriseValue": 55550144512,
    "profitMargins": 0.03196,
    "floatShares": 34503245,
    "sharesOutstanding": 51381600,
    "sharesShort": 1941492,
    "sharesShortPriorMonth": 1644402,
    "sharesShortPreviousMonthDate": 1689292800,
    "dateShortInterest": 1692057600,
    "sharesPercentSharesOut": 0.0378,
    "heldPercentInsiders": 0.39249,
    "heldPercentInstitutions": 0.45146,
    "shortRatio": 2.43,
    "impliedSharesOutstanding": 51381600,
    "bookValue": 376.61,
    "priceToBook": 0.07721516,
    "lastFiscalYearEnd": 1672444800,
    "nextFiscalYearEnd": 1703980800,
    "mostRecentQuarter": 1688083200,
    "netIncomeToCommon": 3309591040,
    "trailingEps": 8.57,
    "forwardEps": 8.39,
    "pegRatio": 0.09,
    "enterpriseToRevenue": 0.537,
    "enterpriseToEbitda": 7.6,
    "52WeekChange": -0.5276921,
    "SandP52WeekChange": 0.08443928,
    "exchange": "NYQ",
    "quoteType": "EQUITY",
    "symbol": "JKS",
    "underlyingSymbol": "JKS",
    "shortName": "JinkoSolar Holding Company Limi",
    "longName": "JinkoSolar Holding Co., Ltd.",
    "firstTradeDateEpochUtc": 1273843800,
    "timeZoneFullName": "America/New_York",
    "timeZoneShortName": "EDT",
    "uuid": "c22249d4-b3bf-3182-bf63-2becef192eba",
    "messageBoardId": "finmb_49547584",
    "gmtOffSetMilliseconds": -14400000,
    "currentPrice": 29.08,
    "targetHighPrice": 77.0,
    "targetLowPrice": 19.32,
    "targetMeanPrice": 53.26,
    "targetMedianPrice": 54.96,
    "recommendationMean": 2.5,
    "recommendationKey": "buy",
    "numberOfAnalystOpinions": 9,
    "totalCash": 14782578688,
    "totalCashPerShare": 287.702,
    "ebitda": 7308788736,
    "totalDebt": 56742932480,
    "quickRatio": 0.563,
    "currentRatio": 1.111,
    "totalRevenue": 103535534080,
    "debtToEquity": 180.443,
    "revenuePerShare": 2049.503,
    "returnOnAssets": 0.02298,
    "returnOnEquity": 0.1999,
    "grossProfits": 12346623000,
    "revenueGrowth": 0.629,
    "grossMargins": 0.15554,
    "ebitdaMargins": 0.07059,
    "operatingMargins": 0.04054,
    "financialCurrency": "CNY",
    "trailingPegRatio": null,
    "parent_etfs": [
        "CTEC"
    ]
}