{
    "address1": "One Bowerman Drive",
    "city": "Beaverton",
    "state": "OR",
    "zip": "97005-6453",
    "country": "United States",
    "phone": "503 671 6453",
    "website": "https://www.nike.com",
    "industry": "Footwear & Accessories",
    "sector": "Consumer Cyclical",
    "longBusinessSummary": "NIKE, Inc., together with its subsidiaries, designs, develops, markets, and sells athletic footwear, apparel, equipment, accessories, and services worldwide. The company provides athletic and casual footwear, apparel, and accessories under the Jumpman trademark; and casual sneakers, apparel, and accessories under the Converse, Chuck Taylor, All Star, One Star, Star Chevron, and Jack Purcell trademarks. It also sells a line of performance equipment and accessories comprising bags, sport balls, socks, eyewear, timepieces, digital devices, bats, gloves, protective equipment, and other equipment for sports activities under the NIKE brand; and various plastic products to other manufacturers. In addition, the company markets apparel with licensed college and professional team, and league logos, as well as sells sports apparel; and licenses unaffiliated parties to manufacture and sell apparel, digital devices, and applications and other equipment for sports activities under NIKE-owned trademarks. It sells its products to footwear stores; sporting goods stores; athletic specialty stores; department stores; skate, tennis, and golf shops; and other retail accounts through NIKE-owned retail stores, digital platforms, independent distributors, licensees, and sales representatives. NIKE, Inc. was founded in 1964 and is headquartered in Beaverton, Oregon.",
    "fullTimeEmployees": 83700,
    "companyOfficers": [
        {
            "maxAge": 1,
            "name": "Mr. Mark G. Parker",
            "age": 66,
            "title": "Exec. Chairman",
            "yearBorn": 1956,
            "fiscalYear": 2023,
            "totalPay": 7638047,
            "exercisedValue": 19443600,
            "unexercisedValue": 72487264
        },
        {
            "maxAge": 1,
            "name": "Mr. John J. Donahoe II",
            "age": 61,
            "title": "Pres, CEO & Director",
            "yearBorn": 1961,
            "fiscalYear": 2023,
            "totalPay": 12322059,
            "exercisedValue": 0,
            "unexercisedValue": 3846427
        },
        {
            "maxAge": 1,
            "name": "Mr. Matthew  Friend",
            "age": 44,
            "title": "Exec. VP & CFO",
            "yearBorn": 1978,
            "fiscalYear": 2023,
            "totalPay": 3661404,
            "exercisedValue": 0,
            "unexercisedValue": 4339626
        },
        {
            "maxAge": 1,
            "name": "Ms. Heidi  O'Neill",
            "age": 56,
            "title": "Pres of Consumer, Product & Brand",
            "yearBorn": 1966,
            "fiscalYear": 2023,
            "totalPay": 3690250,
            "exercisedValue": 0,
            "unexercisedValue": 2007165
        },
        {
            "maxAge": 1,
            "name": "Mr. Andrew  Campion",
            "age": 50,
            "title": "Managing Director of Strategic Bus. Ventures",
            "yearBorn": 1972,
            "fiscalYear": 2023,
            "totalPay": 3690250,
            "exercisedValue": 0,
            "unexercisedValue": 10984705
        },
        {
            "maxAge": 1,
            "name": "Mr. Philip H. Knight",
            "age": 84,
            "title": "Co-Founder & Chairman Emeritus",
            "yearBorn": 1938,
            "fiscalYear": 2005,
            "exercisedValue": 0,
            "unexercisedValue": 0
        },
        {
            "maxAge": 1,
            "name": "Ms. Johanna  Nielsen",
            "age": 44,
            "title": "VP of Controlling & Principal Accounting Officer",
            "yearBorn": 1978,
            "exercisedValue": 0,
            "unexercisedValue": 0
        },
        {
            "maxAge": 1,
            "name": "Mr. Paul  Trussell C.F.A.",
            "title": "VP of Investor Relations & Strategic Fin.",
            "exercisedValue": 0,
            "unexercisedValue": 0
        },
        {
            "maxAge": 1,
            "name": "Ms. Ann M. Miller",
            "age": 47,
            "title": "Exec. VP & Chief Legal Officer",
            "yearBorn": 1975,
            "exercisedValue": 0,
            "unexercisedValue": 0
        },
        {
            "maxAge": 1,
            "name": "Mr. KeJuan  Wilkins",
            "title": "Exec. VP & Chief Communications Officer",
            "exercisedValue": 0,
            "unexercisedValue": 0
        }
    ],
    "auditRisk": 9,
    "boardRisk": 10,
    "compensationRisk": 2,
    "shareHolderRightsRisk": 7,
    "overallRisk": 8,
    "governanceEpochDate": 1693526400,
    "compensationAsOfEpochDate": 1703980800,
    "maxAge": 86400,
    "priceHint": 2,
    "previousClose": 97.93,
    "open": 98.1,
    "dayLow": 97.2775,
    "dayHigh": 98.1344,
    "regularMarketPreviousClose": 97.93,
    "regularMarketOpen": 98.1,
    "regularMarketDayLow": 97.2775,
    "regularMarketDayHigh": 98.1344,
    "dividendRate": 1.36,
    "dividendYield": 0.0139,
    "exDividendDate": 1693526400,
    "payoutRatio": 0.4102,
    "fiveYearAvgDividendYield": 0.96,
    "beta": 1.120331,
    "trailingPE": 30.23839,
    "forwardPE": 22.248291,
    "volume": 6435533,
    "regularMarketVolume": 6435533,
    "averageVolume": 7760979,
    "averageVolume10days": 6932330,
    "averageDailyVolume10Day": 6932330,
    "bid": 0.0,
    "ask": 0.0,
    "bidSize": 800,
    "askSize": 1000,
    "marketCap": 149432172544,
    "fiftyTwoWeekLow": 82.22,
    "fiftyTwoWeekHigh": 131.31,
    "priceToSalesTrailing12Months": 2.9176285,
    "fiftyDayAverage": 105.9862,
    "twoHundredDayAverage": 115.1716,
    "trailingAnnualDividendRate": 1.325,
    "trailingAnnualDividendYield": 0.013530073,
    "currency": "USD",
    "enterpriseValue": 150901325824,
    "profitMargins": 0.09899,
    "floatShares": 1207346495,
    "sharesOutstanding": 1225069952,
    "sharesShort": 16216636,
    "sharesShortPriorMonth": 16907912,
    "sharesShortPreviousMonthDate": 1689292800,
    "dateShortInterest": 1692057600,
    "sharesPercentSharesOut": 0.0106,
    "heldPercentInsiders": 0.0139999995,
    "heldPercentInstitutions": 0.83726,
    "shortRatio": 2.75,
    "shortPercentOfFloat": 0.0164,
    "bookValue": 9.142,
    "priceToBook": 10.683658,
    "lastFiscalYearEnd": 1685491200,
    "nextFiscalYearEnd": 1717113600,
    "mostRecentQuarter": 1685491200,
    "earningsQuarterlyGrowth": -0.284,
    "netIncomeToCommon": 5070000128,
    "trailingEps": 3.23,
    "forwardEps": 4.39,
    "pegRatio": 1.74,
    "lastSplitFactor": "2:1",
    "lastSplitDate": 1450915200,
    "enterpriseToRevenue": 2.946,
    "enterpriseToEbitda": 22.277,
    "exchange": "NYQ",
    "quoteType": "EQUITY",
    "symbol": "NKE",
    "underlyingSymbol": "NKE",
    "shortName": "Nike, Inc.",
    "longName": "NIKE, Inc.",
    "firstTradeDateEpochUtc": 344615400,
    "timeZoneFullName": "America/New_York",
    "timeZoneShortName": "EDT",
    "gmtOffSetMilliseconds": -14400000,
    "currentPrice": 97.67,
    "targetHighPrice": 151.87,
    "targetLowPrice": 91.0,
    "targetMeanPrice": 125.93,
    "targetMedianPrice": 128.0,
    "recommendationMean": 2.3,
    "recommendationKey": "buy",
    "numberOfAnalystOpinions": 31,
    "totalCash": 10675000320,
    "totalCashPerShare": 6.977,
    "ebitda": 6774000128,
    "totalDebt": 12144000000,
    "quickRatio": 1.6,
    "currentRatio": 2.723,
    "totalRevenue": 51216998400,
    "debtToEquity": 86.718,
    "revenuePerShare": 33.009,
    "returnOnAssets": 0.094969995,
    "returnOnEquity": 0.34625,
    "freeCashflow": 3873999872,
    "operatingCashflow": 5840999936,
    "earningsGrowth": -0.269,
    "revenueGrowth": 0.048,
    "grossMargins": 0.43525,
    "ebitdaMargins": 0.13226,
    "operatingMargins": 0.11549,
    "financialCurrency": "USD",
    "trailingPegRatio": 1.7827,
    "parent_etfs": [
        "BFIT",
        "MILN"
    ]
}