{
    "address1": "5260 California Avenue",
    "city": "Irvine",
    "state": "CA",
    "zip": "92617",
    "country": "United States",
    "phone": "949 231 3000",
    "website": "https://www.skyworksinc.com",
    "industry": "Semiconductors",
    "industryDisp": "Semiconductors",
    "sector": "Technology",
    "sectorDisp": "Technology",
    "longBusinessSummary": "Skyworks Solutions, Inc., together with its subsidiaries, designs, develops, manufactures, and markets proprietary semiconductor products in the United States, China, South Korea, Taiwan, Europe, the Middle East, Africa, and the rest of Asia-Pacific. Its product portfolio includes amplifiers, antenna tuners, attenuators, automotive tuners and digital radios, clocks and timings, circulators/isolators, DC/DC converters, demodulators, detectors, diodes, wireless analog system on chip products, directional couplers, diversity receive modules, filters, front-end modules, hybrids, light emitting diode drivers, low noise amplifiers, mixers, modulators, optocouplers/optoisolators, phase locked loops, phase shifters, power dividers/combiners, receivers, switches, synthesizers, timing devices, technical ceramics, voltage controlled oscillators/synthesizers, and voltage regulators. The company provides its products for the usage in aerospace, automotive, broadband, cellular infrastructure, connected home, entertainment and gaming, industrial, medical, military, smartphone, tablet, and wearable markets. It sells its products through direct sales force, electronic component distributors, and independent sales representatives. Skyworks Solutions, Inc. was founded in 1962 and is based in Irvine, California.",
    "fullTimeEmployees": 11150,
    "companyOfficers": [
        {
            "maxAge": 1,
            "name": "Mr. Liam K. Griffin",
            "age": 55,
            "title": "CEO, Pres & Chairman",
            "yearBorn": 1967,
            "fiscalYear": 2022,
            "totalPay": 3579369,
            "exercisedValue": 0,
            "unexercisedValue": 0
        },
        {
            "maxAge": 1,
            "name": "Mr. Kris  Sennesael",
            "age": 53,
            "title": "Sr. VP & CFO",
            "yearBorn": 1969,
            "fiscalYear": 2022,
            "totalPay": 1390782,
            "exercisedValue": 0,
            "unexercisedValue": 499180
        },
        {
            "maxAge": 1,
            "name": "Dr. Reza  Kasnavi",
            "age": 49,
            "title": "Sr. VP of Technology & Manufacturing",
            "yearBorn": 1973,
            "fiscalYear": 2022,
            "totalPay": 1184983,
            "exercisedValue": 0,
            "unexercisedValue": 0
        },
        {
            "maxAge": 1,
            "name": "Mr. Robert John Terry",
            "age": 56,
            "title": "Sr. VP, Gen. Counsel & Sec.",
            "yearBorn": 1966,
            "fiscalYear": 2022,
            "totalPay": 1101474,
            "exercisedValue": 8398,
            "unexercisedValue": 0
        },
        {
            "maxAge": 1,
            "name": "Mr. Carlos S. Bori",
            "age": 51,
            "title": "Sr. VP of Sales & Marketing",
            "yearBorn": 1971,
            "fiscalYear": 2022,
            "totalPay": 1088364,
            "exercisedValue": 0,
            "unexercisedValue": 0
        },
        {
            "maxAge": 1,
            "name": "Mr. Philip Matthew Carter",
            "age": 44,
            "title": "Principal Accounting Officer, VP & Corp. Controller",
            "yearBorn": 1978,
            "exercisedValue": 0,
            "unexercisedValue": 0
        },
        {
            "maxAge": 1,
            "name": "Mr. Mitchell J. Haws",
            "age": 58,
            "title": "VP of Investor Relations",
            "yearBorn": 1964,
            "exercisedValue": 0,
            "unexercisedValue": 0
        },
        {
            "maxAge": 1,
            "name": "Ms. Karilee A. Durham",
            "age": 53,
            "title": "Sr. VP of HR",
            "yearBorn": 1969,
            "fiscalYear": 2021,
            "exercisedValue": 0,
            "unexercisedValue": 0
        },
        {
            "maxAge": 1,
            "name": "Mr. Joel R. King",
            "age": 48,
            "title": "Sr. VP & GM of Mobile Solutions Bus.",
            "yearBorn": 1974,
            "exercisedValue": 0,
            "unexercisedValue": 0
        },
        {
            "maxAge": 1,
            "name": "Mr. Yusuf  Jamal",
            "age": 45,
            "title": "Sr. VP & GM of Diversified Analog Solutions",
            "yearBorn": 1977,
            "exercisedValue": 0,
            "unexercisedValue": 0
        }
    ],
    "auditRisk": 9,
    "boardRisk": 8,
    "compensationRisk": 9,
    "shareHolderRightsRisk": 9,
    "overallRisk": 9,
    "governanceEpochDate": 1693526400,
    "compensationAsOfEpochDate": 1672444800,
    "maxAge": 86400,
    "priceHint": 2,
    "previousClose": 98.38,
    "open": 98.5,
    "dayLow": 98.175,
    "dayHigh": 99.46,
    "regularMarketPreviousClose": 98.38,
    "regularMarketOpen": 98.5,
    "regularMarketDayLow": 98.175,
    "regularMarketDayHigh": 99.46,
    "dividendRate": 2.72,
    "dividendYield": 0.0274,
    "exDividendDate": 1693180800,
    "payoutRatio": 0.3821,
    "fiveYearAvgDividendYield": 1.73,
    "beta": 1.285615,
    "trailingPE": 15.312789,
    "forwardPE": 11.042222,
    "volume": 2062445,
    "regularMarketVolume": 2062445,
    "averageVolume": 1624287,
    "averageVolume10days": 1633270,
    "averageDailyVolume10Day": 1633270,
    "bid": 0.0,
    "ask": 0.0,
    "bidSize": 900,
    "askSize": 900,
    "marketCap": 15840475136,
    "fiftyTwoWeekLow": 76.16,
    "fiftyTwoWeekHigh": 123.69,
    "priceToSalesTrailing12Months": 3.1933222,
    "fiftyDayAverage": 109.208,
    "twoHundredDayAverage": 106.22775,
    "trailingAnnualDividendRate": 2.48,
    "trailingAnnualDividendYield": 0.025208376,
    "currency": "USD",
    "enterpriseValue": 16816234496,
    "profitMargins": 0.20969999,
    "floatShares": 158799634,
    "sharesOutstanding": 159392992,
    "sharesShort": 2553257,
    "sharesShortPriorMonth": 3519156,
    "sharesShortPreviousMonthDate": 1689292800,
    "dateShortInterest": 1692057600,
    "sharesPercentSharesOut": 0.016,
    "heldPercentInsiders": 0.0031299999,
    "heldPercentInstitutions": 0.8337,
    "shortRatio": 1.55,
    "shortPercentOfFloat": 0.0182,
    "impliedSharesOutstanding": 159392992,
    "bookValue": 36.921,
    "priceToBook": 2.6916928,
    "lastFiscalYearEnd": 1664496000,
    "nextFiscalYearEnd": 1696032000,
    "mostRecentQuarter": 1688083200,
    "earningsQuarterlyGrowth": -0.267,
    "netIncomeToCommon": 1040200000,
    "trailingEps": 6.49,
    "forwardEps": 9.0,
    "pegRatio": 0.78,
    "lastSplitFactor": "2:1",
    "lastSplitDate": 956188800,
    "enterpriseToRevenue": 3.39,
    "enterpriseToEbitda": 9.496,
    "52WeekChange": -0.040918767,
    "SandP52WeekChange": 0.08443928,
    "lastDividendValue": 0.68,
    "lastDividendDate": 1693180800,
    "exchange": "NMS",
    "quoteType": "EQUITY",
    "symbol": "SWKS",
    "underlyingSymbol": "SWKS",
    "shortName": "Skyworks Solutions, Inc.",
    "longName": "Skyworks Solutions, Inc.",
    "firstTradeDateEpochUtc": 463411800,
    "timeZoneFullName": "America/New_York",
    "timeZoneShortName": "EDT",
    "uuid": "3e3573db-84b3-3f81-a794-983ed41c6529",
    "messageBoardId": "finmb_1462309",
    "gmtOffSetMilliseconds": -14400000,
    "currentPrice": 99.38,
    "targetHighPrice": 176.0,
    "targetLowPrice": 99.0,
    "targetMeanPrice": 120.51,
    "targetMedianPrice": 118.0,
    "recommendationMean": 2.5,
    "recommendationKey": "buy",
    "numberOfAnalystOpinions": 26,
    "totalCash": 736499968,
    "totalCashPerShare": 4.621,
    "ebitda": 1770899968,
    "totalDebt": 1712300032,
    "quickRatio": 1.791,
    "currentRatio": 3.825,
    "totalRevenue": 4960500224,
    "debtToEquity": 29.131,
    "revenuePerShare": 31.105,
    "returnOnAssets": 0.095319994,
    "returnOnEquity": 0.18621,
    "grossProfits": 2604300000,
    "freeCashflow": 906875008,
    "operatingCashflow": 1727200000,
    "earningsGrowth": -0.265,
    "revenueGrowth": -0.131,
    "grossMargins": 0.46322,
    "ebitdaMargins": 0.357,
    "operatingMargins": 0.26378,
    "financialCurrency": "USD",
    "trailingPegRatio": 1.1382,
    "parent_etfs": [
        "SNSR"
    ]
}