{
    "address1": "201 Brookline Avenue",
    "address2": "Suite 601",
    "city": "Cambridge",
    "state": "MA",
    "zip": "02215",
    "country": "United States",
    "phone": "617 603 0070",
    "website": "https://www.vervetx.com",
    "industry": "Biotechnology",
    "sector": "Healthcare",
    "longBusinessSummary": "Verve Therapeutics, Inc., a genetic medicines company, engages in developing gene editing medicines for patients to treat cardiovascular diseases. Its lead product candidate is VERVE-101, a single-course gene editing treatment that permanently turns off the PCSK9 gene in the liver. The company also engages in the development of ANGPTL3 program to permanently turn off the ANGPTL3 gene in the liver. It has a collaboration and license agreement with Beam Therapeutics Inc.; a development and option agreement with Acuitas Therapeutics, Inc.; and a Cas9 license agreement with The Broad Institute and the President and Fellows of Harvard College. The company was formerly known as Endcadia, Inc. and changed its name to Verve Therapeutics, Inc. in January 2019. Verve Therapeutics, Inc. was incorporated in 2018 and is headquartered in Cambridge, Massachusetts.",
    "fullTimeEmployees": 204,
    "companyOfficers": [
        {
            "maxAge": 1,
            "name": "Dr. Burt A. Adelman M.D.",
            "age": 70,
            "title": "Co-Founder & Independent Chairman",
            "yearBorn": 1952,
            "fiscalYear": 2022,
            "totalPay": 87545,
            "exercisedValue": 0,
            "unexercisedValue": 0
        },
        {
            "maxAge": 1,
            "name": "Dr. Sekar  Kathiresan M.D.",
            "age": 50,
            "title": "Co-Founder, CEO & Director",
            "yearBorn": 1972,
            "fiscalYear": 2022,
            "totalPay": 899552,
            "exercisedValue": 0,
            "unexercisedValue": 10485177
        },
        {
            "maxAge": 1,
            "name": "Mr. Andrew D. Ashe J.D.",
            "age": 55,
            "title": "Pres, COO & Gen. Counsel",
            "yearBorn": 1967,
            "fiscalYear": 2022,
            "totalPay": 703848,
            "exercisedValue": 0,
            "unexercisedValue": 2096535
        },
        {
            "maxAge": 1,
            "name": "Dr. Andrew  Bellinger M.D., Ph.D.",
            "age": 44,
            "title": "Chief Scientific Officer & Chief Medical Officer",
            "yearBorn": 1978,
            "fiscalYear": 2022,
            "totalPay": 703848,
            "exercisedValue": 0,
            "unexercisedValue": 3195674
        },
        {
            "maxAge": 1,
            "name": "Dr. Kiran  Musunuru M.D., M.P.H., Ph.D.",
            "title": "Co-Founder & Sr. Scientific Advisor",
            "exercisedValue": 0,
            "unexercisedValue": 0
        },
        {
            "maxAge": 1,
            "name": "Dr. J. Keith Joung M.D., Ph.D.",
            "title": "Co-Founder",
            "exercisedValue": 0,
            "unexercisedValue": 0
        },
        {
            "maxAge": 1,
            "name": "Dr. Anthony  Philippakis M.D., Ph.D.",
            "title": "Co-Founder & Scientific Advisory Board Member",
            "fiscalYear": 2021,
            "exercisedValue": 0,
            "unexercisedValue": 0
        },
        {
            "maxAge": 1,
            "name": "Dr. Barry S. Ticho FACC, M.D., Ph.D.",
            "age": 61,
            "title": "Co-Founder",
            "yearBorn": 1961,
            "exercisedValue": 0,
            "unexercisedValue": 0
        },
        {
            "maxAge": 1,
            "name": "Mr. Issi  Rozen M.B.A.",
            "title": "Co-Founder & Strategic Advisor",
            "exercisedValue": 0,
            "unexercisedValue": 0
        },
        {
            "maxAge": 1,
            "name": "Ms. Allison  Dorval",
            "age": 46,
            "title": "CFO & Principal Accounting Officer",
            "yearBorn": 1976,
            "fiscalYear": 2021,
            "exercisedValue": 0,
            "unexercisedValue": 0
        }
    ],
    "auditRisk": 7,
    "boardRisk": 8,
    "compensationRisk": 7,
    "shareHolderRightsRisk": 8,
    "overallRisk": 8,
    "governanceEpochDate": 1693526400,
    "compensationAsOfEpochDate": 1672444800,
    "maxAge": 86400,
    "priceHint": 2,
    "previousClose": 12.59,
    "open": 12.66,
    "dayLow": 12.36,
    "dayHigh": 12.87,
    "regularMarketPreviousClose": 12.59,
    "regularMarketOpen": 12.66,
    "regularMarketDayLow": 12.36,
    "regularMarketDayHigh": 12.87,
    "payoutRatio": 0.0,
    "beta": 1.700677,
    "forwardPE": -3.417344,
    "volume": 306636,
    "regularMarketVolume": 306636,
    "averageVolume": 649146,
    "averageVolume10days": 652230,
    "averageDailyVolume10Day": 652230,
    "bid": 0.0,
    "ask": 0.0,
    "bidSize": 800,
    "askSize": 800,
    "marketCap": 803525568,
    "fiftyTwoWeekLow": 11.97,
    "fiftyTwoWeekHigh": 41.96,
    "priceToSalesTrailing12Months": 147.76123,
    "fiftyDayAverage": 17.2182,
    "twoHundredDayAverage": 18.27155,
    "trailingAnnualDividendRate": 0.0,
    "trailingAnnualDividendYield": 0.0,
    "currency": "USD",
    "enterpriseValue": 418914112,
    "profitMargins": 0.0,
    "floatShares": 46783514,
    "sharesOutstanding": 63721300,
    "sharesShort": 11168205,
    "sharesShortPriorMonth": 11895740,
    "sharesShortPreviousMonthDate": 1689292800,
    "dateShortInterest": 1692057600,
    "sharesPercentSharesOut": 0.1753,
    "heldPercentInsiders": 0.10321999,
    "heldPercentInstitutions": 1.01889,
    "shortRatio": 19.88,
    "shortPercentOfFloat": 0.2488,
    "bookValue": 7.496,
    "priceToBook": 1.6822305,
    "lastFiscalYearEnd": 1672444800,
    "nextFiscalYearEnd": 1703980800,
    "mostRecentQuarter": 1688083200,
    "netIncomeToCommon": -192232992,
    "trailingEps": -3.15,
    "forwardEps": -3.69,
    "enterpriseToRevenue": 77.035,
    "enterpriseToEbitda": -2.05,
    "exchange": "NMS",
    "quoteType": "EQUITY",
    "symbol": "VERV",
    "underlyingSymbol": "VERV",
    "shortName": "Verve Therapeutics, Inc.",
    "longName": "Verve Therapeutics, Inc.",
    "firstTradeDateEpochUtc": 1623936600,
    "timeZoneFullName": "America/New_York",
    "timeZoneShortName": "EDT",
    "gmtOffSetMilliseconds": -14400000,
    "currentPrice": 12.61,
    "targetHighPrice": 75.0,
    "targetLowPrice": 13.0,
    "targetMeanPrice": 40.18,
    "targetMedianPrice": 32.0,
    "recommendationMean": 2.0,
    "recommendationKey": "buy",
    "numberOfAnalystOpinions": 11,
    "totalCash": 462476000,
    "totalCashPerShare": 7.258,
    "ebitda": -204306000,
    "totalDebt": 77865000,
    "quickRatio": 14.065,
    "currentRatio": 14.322,
    "totalRevenue": 5438000,
    "debtToEquity": 16.737,
    "revenuePerShare": 0.09,
    "returnOnAssets": -0.28521,
    "returnOnEquity": -0.50484,
    "grossProfits": -128154000,
    "freeCashflow": -117594496,
    "operatingCashflow": -159124992,
    "grossMargins": 0.0,
    "ebitdaMargins": 0.0,
    "operatingMargins": -38.32512,
    "financialCurrency": "USD",
    "trailingPegRatio": null,
    "parent_etfs": [
        "GNOM"
    ]
}